elara/__init__.py
elara/db_thread.py
elara/elara.py
elara/elarautil.py
elara/exceptions.py
elara/hashtables.py
elara/keys.py
elara/lists.py
elara/lru.py
elara/shared.py
elara/status.py
elara/strings.py
elara-0.5.5.dist-info/LICENSE
elara-0.5.5.dist-info/METADATA
elara-0.5.5.dist-info/WHEEL
elara-0.5.5.dist-info/top_level.txt
elara-0.5.5.dist-info/RECORD
