Metadata-Version: 2.1
Name: elara
Version: 0.5.5
Summary: Elara DB is an easy to use, lightweight key-value database written for python that can also be used as a fast in-memory cache for JSON-serializable data. Includes various methods and features to manipulate data structures in-memory, protect database files and export data.
Home-page: https://github.com/saurabh0719/elara
Author: Saurabh Pujari
Author-email: saurabhpuj99@gmail.com
License: three-clause BSD
Project-URL: Documentation, https://github.com/saurabh0719/elara#readme
Project-URL: Source, https://github.com/saurabh0719/elara
Keywords: database,key-value,storage,file storage,key-value database,nosql,nosql database,cache,in-memory cache,file cache
Classifier: Development Status :: 4 - Beta
Classifier: Intended Audience :: Developers
Classifier: Topic :: Database
Classifier: License :: OSI Approved :: BSD License
Classifier: Programming Language :: Python
License-File: LICENSE
Requires-Dist: cryptography
Requires-Dist: msgpack
Requires-Dist: safer
